[{"total": 781, "polarity": 82.03677191011845, "subjectivity": 243.69121469117314, "subreddit": "aww"}, {"total": 2565, "polarity": 234.66650499580447, "subjectivity": 788.9465231797822, "subreddit": "teenagers"}, {"total": 1391, "polarity": 151.21269702919125, "subjectivity": 598.8946038193716, "subreddit": "unpopularopinion"}, {"total": 1193, "polarity": 83.3258250429434, "subjectivity": 437.162883846271, "subreddit": "soccer"}, {"total": 641, "polarity": 53.51211309523812, "subjectivity": 135.50917658730157, "subreddit": "Market76"}, {"total": 606, "polarity": 53.0835932443357, "subjectivity": 193.41147893703334, "subreddit": "mildlyinteresting"}, {"total": 8721, "polarity": 543.7862569595959, "subjectivity": 2721.2784717052473, "subreddit": "AskReddit"}, {"total": 1498, "polarity": 117.12631304603168, "subjectivity": 660.1130880039894, "subreddit": "AmItheAsshole"}, {"total": 2273, "polarity": 76.66189017584885, "subjectivity": 502.34969924267716, "subreddit": "dankmemes"}, {"total": 2074, "polarity": 104.82477590532854, "subjectivity": 651.2427682197912, "subreddit": "freefolk"}, {"total": 1085, "polarity": 103.31207824192555, "subjectivity": 410.9029524897557, "subreddit": "leagueoflegends"}, {"total": 2827, "polarity": 204.57829431542586, "subjectivity": 759.5134123083849, "subreddit": "memes"}, {"total": 882, "polarity": 60.122012572405275, "subjectivity": 318.33587301192375, "subreddit": "SquaredCircle"}, {"total": 868, "polarity": 217.7816239374049, "subjectivity": 368.8494049931552, "subreddit": "gonewild"}, {"total": 2346, "polarity": 110.17806257310609, "subjectivity": 805.690320458001, "subreddit": "politics"}, {"total": 490, "polarity": 38.48874522402202, "subjectivity": 154.24069644949415, "subreddit": "LiverpoolFC"}, {"total": 989, "polarity": 69.02514286859528, "subjectivity": 338.6040998375521, "subreddit": "Showerthoughts"}, {"total": 1097, "polarity": 34.97478355113021, "subjectivity": 361.1953224597791, "subreddit": "news"}, {"total": 961, "polarity": 90.34524597283226, "subjectivity": 328.35942707100037, "subreddit": "gaming"}, {"total": 1013, "polarity": 109.29949887102366, "subjectivity": 381.8035732984899, "subreddit": "nba"}, {"total": 1373, "polarity": 38.953476352690885, "subjectivity": 431.04805491962566, "subreddit": "The_Donald"}, {"total": 761, "polarity": 46.07775227604767, "subjectivity": 265.70936343595656, "subreddit": "pics"}, {"total": 1286, "polarity": 81.25179813987921, "subjectivity": 459.06510311129307, "subreddit": "worldnews"}, {"total": 809, "polarity": 0.5718253968253965, "subjectivity": 20.321897546897546, "subreddit": "AskOuija"}, {"total": 1116, "polarity": 65.50145296860335, "subjectivity": 346.3968538940117, "subreddit": "funny"}]